{"station":"NeoPower Hot Water","generated":"2026-07-24T04:30:23.827Z","day":{"date":"2026-07-24","now":62,"nowBottom":52,"nowTs":1784867404,"heating":1,"setTemp":70,"mode":null,"min":30,"max":64,"avg":48.4,"minBottom":20,"maxBottom":52,"avgBottom":28.6,"heatingMinutes":270,"cycles":1,"energyKwh":null,"points":[{"s":3437,"t":64,"tb":22,"h":0,"set":null},{"s":3741,"t":63,"tb":22,"h":0,"set":null},{"s":8590,"t":63,"tb":22,"h":0,"set":null},{"s":8783,"t":62,"tb":22,"h":0,"set":null},{"s":9108,"t":63,"tb":22,"h":0,"set":null},{"s":9296,"t":62,"tb":22,"h":0,"set":null},{"s":9386,"t":63,"tb":22,"h":0,"set":null},{"s":9400,"t":62,"tb":22,"h":0,"set":null},{"s":10103,"t":62,"tb":22,"h":0,"set":null},{"s":10235,"t":62,"tb":22,"h":0,"set":null},{"s":10296,"t":62,"tb":22,"h":0,"set":null},{"s":10386,"t":62,"tb":22,"h":0,"set":null},{"s":10434,"t":62,"tb":22,"h":0,"set":null},{"s":10524,"t":62,"tb":23,"h":0,"set":null},{"s":10581,"t":62,"tb":22,"h":0,"set":null},{"s":10638,"t":62,"tb":22,"h":0,"set":null},{"s":10706,"t":62,"tb":23,"h":0,"set":null},{"s":10769,"t":62,"tb":23,"h":0,"set":null},{"s":10824,"t":62,"tb":22,"h":0,"set":null},{"s":10883,"t":62,"tb":23,"h":0,"set":null},{"s":10934,"t":62,"tb":23,"h":0,"set":null},{"s":11008,"t":62,"tb":23,"h":0,"set":null},{"s":11062,"t":62,"tb":23,"h":0,"set":null},{"s":11655,"t":62,"tb":23,"h":0,"set":null},{"s":17274,"t":62,"tb":23,"h":0,"set":null},{"s":17423,"t":62,"tb":23,"h":0,"set":null},{"s":17456,"t":62,"tb":23,"h":0,"set":null},{"s":17547,"t":62,"tb":23,"h":0,"set":null},{"s":17607,"t":62,"tb":24,"h":0,"set":null},{"s":17665,"t":62,"tb":24,"h":0,"set":null},{"s":17729,"t":62,"tb":23,"h":0,"set":null},{"s":17783,"t":62,"tb":23,"h":0,"set":null},{"s":17832,"t":62,"tb":24,"h":0,"set":null},{"s":17903,"t":62,"tb":24,"h":0,"set":null},{"s":17941,"t":62,"tb":24,"h":0,"set":null},{"s":18019,"t":62,"tb":24,"h":0,"set":null},{"s":18074,"t":62,"tb":24,"h":0,"set":null},{"s":18148,"t":62,"tb":23,"h":0,"set":null},{"s":18150,"t":62,"tb":24,"h":0,"set":null},{"s":18304,"t":62,"tb":24,"h":0,"set":null},{"s":18397,"t":62,"tb":24,"h":0,"set":null},{"s":19977,"t":61,"tb":24,"h":0,"set":null},{"s":22805,"t":61,"tb":24,"h":0,"set":70},{"s":23309,"t":60,"tb":23,"h":0,"set":null},{"s":23315,"t":60,"tb":22,"h":0,"set":null},{"s":23429,"t":59,"tb":22,"h":0,"set":null},{"s":23489,"t":59,"tb":21,"h":0,"set":null},{"s":23608,"t":58,"tb":21,"h":0,"set":null},{"s":23680,"t":57,"tb":21,"h":0,"set":null},{"s":23796,"t":56,"tb":21,"h":0,"set":null},{"s":23855,"t":55,"tb":21,"h":0,"set":null},{"s":24066,"t":54,"tb":21,"h":0,"set":null},{"s":24134,"t":54,"tb":21,"h":0,"set":null},{"s":24209,"t":54,"tb":20,"h":0,"set":null},{"s":24269,"t":54,"tb":21,"h":0,"set":null},{"s":24318,"t":54,"tb":21,"h":0,"set":null},{"s":24385,"t":54,"tb":21,"h":0,"set":null},{"s":24446,"t":54,"tb":20,"h":0,"set":null},{"s":24508,"t":54,"tb":21,"h":0,"set":null},{"s":24567,"t":54,"tb":20,"h":0,"set":null},{"s":24624,"t":54,"tb":20,"h":0,"set":null},{"s":24678,"t":54,"tb":20,"h":0,"set":null},{"s":24748,"t":54,"tb":21,"h":0,"set":null},{"s":24751,"t":54,"tb":20,"h":0,"set":null},{"s":24869,"t":54,"tb":20,"h":0,"set":null},{"s":24924,"t":54,"tb":20,"h":0,"set":null},{"s":24942,"t":54,"tb":20,"h":0,"set":null},{"s":25046,"t":54,"tb":20,"h":0,"set":null},{"s":25140,"t":54,"tb":20,"h":0,"set":null},{"s":25283,"t":54,"tb":20,"h":0,"set":null},{"s":25518,"t":54,"tb":20,"h":0,"set":null},{"s":25577,"t":54,"tb":20,"h":0,"set":null},{"s":25649,"t":54,"tb":20,"h":0,"set":null},{"s":26067,"t":54,"tb":20,"h":0,"set":null},{"s":26125,"t":53,"tb":20,"h":0,"set":null},{"s":26166,"t":54,"tb":20,"h":0,"set":null},{"s":26373,"t":53,"tb":20,"h":0,"set":null},{"s":27183,"t":53,"tb":20,"h":0,"set":null},{"s":27496,"t":53,"tb":20,"h":0,"set":null},{"s":27569,"t":53,"tb":21,"h":0,"set":null},{"s":27574,"t":53,"tb":20,"h":0,"set":null},{"s":27681,"t":53,"tb":20,"h":0,"set":null},{"s":27749,"t":53,"tb":21,"h":0,"set":null},{"s":27804,"t":53,"tb":20,"h":0,"set":null},{"s":27934,"t":53,"tb":20,"h":0,"set":null},{"s":28035,"t":53,"tb":20,"h":0,"set":null},{"s":28107,"t":53,"tb":20,"h":0,"set":null},{"s":28149,"t":53,"tb":20,"h":0,"set":null},{"s":28211,"t":52,"tb":20,"h":0,"set":null},{"s":28251,"t":51,"tb":20,"h":0,"set":null},{"s":28331,"t":50,"tb":20,"h":0,"set":null},{"s":28404,"t":49,"tb":20,"h":0,"set":null},{"s":28452,"t":48,"tb":20,"h":0,"set":null},{"s":28521,"t":47,"tb":20,"h":0,"set":null},{"s":28572,"t":46,"tb":20,"h":0,"set":null},{"s":28622,"t":45,"tb":20,"h":0,"set":null},{"s":28674,"t":44,"tb":20,"h":0,"set":null},{"s":28724,"t":43,"tb":20,"h":0,"set":null},{"s":28815,"t":41,"tb":20,"h":0,"set":null},{"s":28857,"t":40,"tb":20,"h":0,"set":null},{"s":28949,"t":38,"tb":20,"h":0,"set":null},{"s":28990,"t":37,"tb":20,"h":0,"set":null},{"s":29069,"t":35,"tb":20,"h":0,"set":null},{"s":29113,"t":34,"tb":20,"h":0,"set":null},{"s":29157,"t":33,"tb":20,"h":0,"set":null},{"s":29198,"t":32,"tb":20,"h":0,"set":null},{"s":29299,"t":31,"tb":20,"h":0,"set":null},{"s":29396,"t":31,"tb":20,"h":0,"set":null},{"s":29477,"t":31,"tb":20,"h":0,"set":null},{"s":29531,"t":31,"tb":20,"h":0,"set":null},{"s":30113,"t":31,"tb":20,"h":0,"set":null},{"s":33379,"t":30,"tb":20,"h":0,"set":null},{"s":33414,"t":30,"tb":20,"h":0,"set":null},{"s":36017,"t":30,"tb":20,"h":1,"set":null},{"s":36403,"t":31,"tb":20,"h":1,"set":null},{"s":36867,"t":31,"tb":20,"h":1,"set":null},{"s":36916,"t":31,"tb":20,"h":1,"set":null},{"s":36982,"t":31,"tb":21,"h":1,"set":null},{"s":37028,"t":31,"tb":21,"h":1,"set":null},{"s":37284,"t":32,"tb":21,"h":1,"set":null},{"s":37312,"t":32,"tb":21,"h":1,"set":null},{"s":37822,"t":32,"tb":22,"h":1,"set":null},{"s":37846,"t":32,"tb":22,"h":1,"set":null},{"s":38034,"t":33,"tb":22,"h":1,"set":null},{"s":38344,"t":33,"tb":23,"h":1,"set":null},{"s":38483,"t":34,"tb":23,"h":1,"set":null},{"s":38604,"t":34,"tb":23,"h":1,"set":null},{"s":38626,"t":34,"tb":24,"h":1,"set":null},{"s":38908,"t":35,"tb":25,"h":1,"set":null},{"s":39259,"t":35,"tb":25,"h":1,"set":null},{"s":39314,"t":36,"tb":26,"h":1,"set":null},{"s":39508,"t":36,"tb":26,"h":1,"set":null},{"s":39537,"t":36,"tb":27,"h":1,"set":null},{"s":39678,"t":37,"tb":27,"h":1,"set":null},{"s":39912,"t":37,"tb":28,"h":1,"set":null},{"s":40091,"t":38,"tb":28,"h":1,"set":null},{"s":40152,"t":38,"tb":29,"h":1,"set":null},{"s":40459,"t":39,"tb":29,"h":1,"set":null},{"s":40542,"t":39,"tb":30,"h":1,"set":null},{"s":40850,"t":40,"tb":30,"h":1,"set":null},{"s":40937,"t":40,"tb":31,"h":1,"set":null},{"s":41252,"t":41,"tb":31,"h":1,"set":null},{"s":41341,"t":41,"tb":32,"h":1,"set":null},{"s":41637,"t":42,"tb":32,"h":1,"set":null},{"s":41742,"t":42,"tb":33,"h":1,"set":null},{"s":42058,"t":43,"tb":34,"h":1,"set":null},{"s":42330,"t":43,"tb":35,"h":1,"set":null},{"s":42457,"t":44,"tb":35,"h":1,"set":null},{"s":42640,"t":44,"tb":36,"h":1,"set":null},{"s":42888,"t":45,"tb":36,"h":1,"set":null},{"s":42972,"t":45,"tb":37,"h":1,"set":null},{"s":43204,"t":45,"tb":37,"h":1,"set":70},{"s":43330,"t":46,"tb":38,"h":1,"set":null},{"s":43651,"t":46,"tb":39,"h":1,"set":null},{"s":43794,"t":47,"tb":39,"h":1,"set":null},{"s":44001,"t":47,"tb":40,"h":1,"set":null},{"s":44230,"t":48,"tb":40,"h":1,"set":null},{"s":44364,"t":48,"tb":41,"h":1,"set":null},{"s":44446,"t":49,"tb":41,"h":1,"set":null},{"s":44521,"t":48,"tb":41,"h":1,"set":null},{"s":44729,"t":49,"tb":42,"h":1,"set":null},{"s":44744,"t":49,"tb":42,"h":1,"set":null},{"s":45110,"t":49,"tb":43,"h":1,"set":null},{"s":45213,"t":50,"tb":43,"h":1,"set":null},{"s":45554,"t":50,"tb":44,"h":1,"set":null},{"s":45704,"t":51,"tb":44,"h":1,"set":null},{"s":46005,"t":51,"tb":45,"h":1,"set":null},{"s":46268,"t":52,"tb":45,"h":1,"set":null},{"s":46461,"t":52,"tb":46,"h":1,"set":null},{"s":46509,"t":53,"tb":46,"h":1,"set":null},{"s":46959,"t":53,"tb":47,"h":1,"set":null},{"s":47055,"t":54,"tb":47,"h":1,"set":null},{"s":47376,"t":55,"tb":47,"h":1,"set":null},{"s":47546,"t":55,"tb":48,"h":1,"set":null},{"s":47899,"t":55,"tb":49,"h":1,"set":null},{"s":47980,"t":55,"tb":48,"h":1,"set":null},{"s":48044,"t":56,"tb":48,"h":1,"set":null},{"s":48233,"t":56,"tb":49,"h":1,"set":null},{"s":48372,"t":57,"tb":49,"h":1,"set":null},{"s":48844,"t":57,"tb":50,"h":1,"set":null},{"s":49130,"t":58,"tb":50,"h":1,"set":null},{"s":49514,"t":59,"tb":51,"h":1,"set":null},{"s":50183,"t":59,"tb":52,"h":1,"set":null},{"s":50331,"t":60,"tb":52,"h":1,"set":null},{"s":50690,"t":61,"tb":52,"h":1,"set":null},{"s":51117,"t":62,"tb":52,"h":1,"set":null},{"s":51160,"t":61,"tb":52,"h":1,"set":null},{"s":51244,"t":62,"tb":52,"h":1,"set":null},{"s":52204,"t":62,"tb":52,"h":1,"set":70}]},"last24":{"start":1784781004,"startSec":52204,"points":[{"s":0,"t":69,"tb":47,"h":0,"set":70},{"s":5110,"t":69,"tb":47,"h":0,"set":null},{"s":5439,"t":69,"tb":47,"h":0,"set":null},{"s":5532,"t":68,"tb":47,"h":0,"set":null},{"s":5554,"t":69,"tb":47,"h":0,"set":null},{"s":5715,"t":68,"tb":47,"h":0,"set":null},{"s":5726,"t":69,"tb":47,"h":0,"set":null},{"s":6546,"t":68,"tb":47,"h":0,"set":null},{"s":7195,"t":68,"tb":47,"h":0,"set":null},{"s":7823,"t":68,"tb":48,"h":0,"set":null},{"s":7829,"t":68,"tb":47,"h":0,"set":null},{"s":12682,"t":68,"tb":48,"h":0,"set":null},{"s":12689,"t":68,"tb":47,"h":0,"set":null},{"s":13013,"t":68,"tb":47,"h":0,"set":null},{"s":13645,"t":68,"tb":47,"h":0,"set":null},{"s":13925,"t":68,"tb":47,"h":0,"set":null},{"s":14042,"t":68,"tb":47,"h":0,"set":null},{"s":14237,"t":67,"tb":47,"h":0,"set":null},{"s":14400,"t":67,"tb":47,"h":0,"set":70},{"s":14599,"t":68,"tb":47,"h":0,"set":null},{"s":14626,"t":67,"tb":47,"h":0,"set":null},{"s":14956,"t":67,"tb":48,"h":0,"set":null},{"s":15111,"t":67,"tb":47,"h":0,"set":null},{"s":15302,"t":67,"tb":48,"h":0,"set":null},{"s":15365,"t":67,"tb":47,"h":0,"set":null},{"s":15504,"t":67,"tb":47,"h":0,"set":null},{"s":15512,"t":67,"tb":48,"h":0,"set":null},{"s":15662,"t":67,"tb":47,"h":0,"set":null},{"s":15725,"t":67,"tb":48,"h":0,"set":null},{"s":16207,"t":67,"tb":47,"h":0,"set":null},{"s":16231,"t":67,"tb":48,"h":0,"set":null},{"s":16337,"t":67,"tb":48,"h":0,"set":null},{"s":16431,"t":67,"tb":48,"h":0,"set":null},{"s":16520,"t":67,"tb":48,"h":0,"set":null},{"s":16686,"t":67,"tb":48,"h":0,"set":null},{"s":16915,"t":67,"tb":48,"h":0,"set":null},{"s":16969,"t":67,"tb":48,"h":0,"set":null},{"s":17079,"t":67,"tb":48,"h":0,"set":null},{"s":17320,"t":67,"tb":48,"h":0,"set":null},{"s":17572,"t":67,"tb":48,"h":0,"set":null},{"s":18050,"t":67,"tb":48,"h":0,"set":null},{"s":18368,"t":67,"tb":48,"h":0,"set":null},{"s":18919,"t":67,"tb":48,"h":0,"set":null},{"s":19027,"t":67,"tb":48,"h":0,"set":null},{"s":19285,"t":67,"tb":47,"h":0,"set":null},{"s":19293,"t":67,"tb":48,"h":0,"set":null},{"s":19729,"t":67,"tb":48,"h":0,"set":null},{"s":20387,"t":67,"tb":48,"h":0,"set":null},{"s":21940,"t":66,"tb":48,"h":0,"set":null},{"s":22084,"t":66,"tb":48,"h":0,"set":null},{"s":22214,"t":67,"tb":48,"h":0,"set":null},{"s":22273,"t":67,"tb":48,"h":0,"set":null},{"s":22322,"t":66,"tb":48,"h":0,"set":null},{"s":22454,"t":67,"tb":48,"h":0,"set":null},{"s":22467,"t":66,"tb":48,"h":0,"set":null},{"s":22582,"t":67,"tb":48,"h":0,"set":null},{"s":22638,"t":66,"tb":48,"h":0,"set":null},{"s":22936,"t":66,"tb":48,"h":0,"set":null},{"s":23768,"t":66,"tb":48,"h":0,"set":null},{"s":23908,"t":66,"tb":48,"h":0,"set":null},{"s":24365,"t":66,"tb":48,"h":0,"set":null},{"s":24803,"t":66,"tb":48,"h":0,"set":null},{"s":25101,"t":66,"tb":48,"h":0,"set":null},{"s":25133,"t":66,"tb":47,"h":0,"set":null},{"s":25201,"t":66,"tb":48,"h":0,"set":null},{"s":25263,"t":66,"tb":48,"h":0,"set":null},{"s":25754,"t":66,"tb":47,"h":0,"set":null},{"s":25814,"t":66,"tb":47,"h":0,"set":null},{"s":25839,"t":66,"tb":48,"h":0,"set":null},{"s":26002,"t":66,"tb":48,"h":0,"set":null},{"s":26151,"t":66,"tb":47,"h":0,"set":null},{"s":26208,"t":66,"tb":48,"h":0,"set":null},{"s":26412,"t":66,"tb":48,"h":0,"set":null},{"s":26483,"t":66,"tb":48,"h":0,"set":null},{"s":26605,"t":66,"tb":48,"h":0,"set":null},{"s":26809,"t":66,"tb":47,"h":0,"set":null},{"s":26872,"t":66,"tb":48,"h":0,"set":null},{"s":26993,"t":66,"tb":47,"h":0,"set":null},{"s":27029,"t":66,"tb":48,"h":0,"set":null},{"s":27308,"t":66,"tb":48,"h":0,"set":null},{"s":27564,"t":66,"tb":47,"h":0,"set":null},{"s":27727,"t":66,"tb":48,"h":0,"set":null},{"s":27932,"t":66,"tb":47,"h":0,"set":null},{"s":28289,"t":66,"tb":48,"h":0,"set":null},{"s":28368,"t":66,"tb":47,"h":0,"set":null},{"s":28462,"t":66,"tb":48,"h":0,"set":null},{"s":28550,"t":66,"tb":47,"h":0,"set":null},{"s":29084,"t":65,"tb":47,"h":0,"set":null},{"s":29522,"t":66,"tb":47,"h":0,"set":null},{"s":29602,"t":65,"tb":47,"h":0,"set":null},{"s":30296,"t":65,"tb":47,"h":0,"set":null},{"s":32001,"t":65,"tb":42,"h":0,"set":null},{"s":32054,"t":65,"tb":37,"h":0,"set":null},{"s":32114,"t":65,"tb":32,"h":0,"set":null},{"s":32167,"t":65,"tb":30,"h":0,"set":null},{"s":32228,"t":65,"tb":28,"h":0,"set":null},{"s":32299,"t":65,"tb":26,"h":0,"set":null},{"s":32340,"t":65,"tb":25,"h":0,"set":null},{"s":32413,"t":65,"tb":24,"h":0,"set":null},{"s":32505,"t":65,"tb":23,"h":0,"set":null},{"s":32660,"t":65,"tb":22,"h":0,"set":null},{"s":33213,"t":64,"tb":22,"h":0,"set":null},{"s":37633,"t":64,"tb":22,"h":0,"set":null},{"s":37937,"t":63,"tb":22,"h":0,"set":null},{"s":42786,"t":63,"tb":22,"h":0,"set":null},{"s":42979,"t":62,"tb":22,"h":0,"set":null},{"s":43304,"t":63,"tb":22,"h":0,"set":null},{"s":43492,"t":62,"tb":22,"h":0,"set":null},{"s":43582,"t":63,"tb":22,"h":0,"set":null},{"s":43596,"t":62,"tb":22,"h":0,"set":null},{"s":44299,"t":62,"tb":22,"h":0,"set":null},{"s":44431,"t":62,"tb":22,"h":0,"set":null},{"s":44492,"t":62,"tb":22,"h":0,"set":null},{"s":44582,"t":62,"tb":22,"h":0,"set":null},{"s":44630,"t":62,"tb":22,"h":0,"set":null},{"s":44720,"t":62,"tb":23,"h":0,"set":null},{"s":44777,"t":62,"tb":22,"h":0,"set":null},{"s":44834,"t":62,"tb":22,"h":0,"set":null},{"s":44902,"t":62,"tb":23,"h":0,"set":null},{"s":44965,"t":62,"tb":23,"h":0,"set":null},{"s":45020,"t":62,"tb":22,"h":0,"set":null},{"s":45079,"t":62,"tb":23,"h":0,"set":null},{"s":45130,"t":62,"tb":23,"h":0,"set":null},{"s":45204,"t":62,"tb":23,"h":0,"set":null},{"s":45258,"t":62,"tb":23,"h":0,"set":null},{"s":45851,"t":62,"tb":23,"h":0,"set":null},{"s":51470,"t":62,"tb":23,"h":0,"set":null},{"s":51619,"t":62,"tb":23,"h":0,"set":null},{"s":51652,"t":62,"tb":23,"h":0,"set":null},{"s":51743,"t":62,"tb":23,"h":0,"set":null},{"s":51803,"t":62,"tb":24,"h":0,"set":null},{"s":51861,"t":62,"tb":24,"h":0,"set":null},{"s":51925,"t":62,"tb":23,"h":0,"set":null},{"s":51979,"t":62,"tb":23,"h":0,"set":null},{"s":52028,"t":62,"tb":24,"h":0,"set":null},{"s":52099,"t":62,"tb":24,"h":0,"set":null},{"s":52137,"t":62,"tb":24,"h":0,"set":null},{"s":52215,"t":62,"tb":24,"h":0,"set":null},{"s":52270,"t":62,"tb":24,"h":0,"set":null},{"s":52344,"t":62,"tb":23,"h":0,"set":null},{"s":52346,"t":62,"tb":24,"h":0,"set":null},{"s":52500,"t":62,"tb":24,"h":0,"set":null},{"s":52593,"t":62,"tb":24,"h":0,"set":null},{"s":54173,"t":61,"tb":24,"h":0,"set":null},{"s":57001,"t":61,"tb":24,"h":0,"set":70},{"s":57505,"t":60,"tb":23,"h":0,"set":null},{"s":57511,"t":60,"tb":22,"h":0,"set":null},{"s":57625,"t":59,"tb":22,"h":0,"set":null},{"s":57685,"t":59,"tb":21,"h":0,"set":null},{"s":57804,"t":58,"tb":21,"h":0,"set":null},{"s":57876,"t":57,"tb":21,"h":0,"set":null},{"s":57992,"t":56,"tb":21,"h":0,"set":null},{"s":58051,"t":55,"tb":21,"h":0,"set":null},{"s":58262,"t":54,"tb":21,"h":0,"set":null},{"s":58330,"t":54,"tb":21,"h":0,"set":null},{"s":58405,"t":54,"tb":20,"h":0,"set":null},{"s":58465,"t":54,"tb":21,"h":0,"set":null},{"s":58514,"t":54,"tb":21,"h":0,"set":null},{"s":58581,"t":54,"tb":21,"h":0,"set":null},{"s":58642,"t":54,"tb":20,"h":0,"set":null},{"s":58704,"t":54,"tb":21,"h":0,"set":null},{"s":58763,"t":54,"tb":20,"h":0,"set":null},{"s":58820,"t":54,"tb":20,"h":0,"set":null},{"s":58874,"t":54,"tb":20,"h":0,"set":null},{"s":58944,"t":54,"tb":21,"h":0,"set":null},{"s":58947,"t":54,"tb":20,"h":0,"set":null},{"s":59065,"t":54,"tb":20,"h":0,"set":null},{"s":59120,"t":54,"tb":20,"h":0,"set":null},{"s":59138,"t":54,"tb":20,"h":0,"set":null},{"s":59242,"t":54,"tb":20,"h":0,"set":null},{"s":59336,"t":54,"tb":20,"h":0,"set":null},{"s":59479,"t":54,"tb":20,"h":0,"set":null},{"s":59714,"t":54,"tb":20,"h":0,"set":null},{"s":59773,"t":54,"tb":20,"h":0,"set":null},{"s":59845,"t":54,"tb":20,"h":0,"set":null},{"s":60263,"t":54,"tb":20,"h":0,"set":null},{"s":60321,"t":53,"tb":20,"h":0,"set":null},{"s":60362,"t":54,"tb":20,"h":0,"set":null},{"s":60569,"t":53,"tb":20,"h":0,"set":null},{"s":61379,"t":53,"tb":20,"h":0,"set":null},{"s":61692,"t":53,"tb":20,"h":0,"set":null},{"s":61765,"t":53,"tb":21,"h":0,"set":null},{"s":61770,"t":53,"tb":20,"h":0,"set":null},{"s":61877,"t":53,"tb":20,"h":0,"set":null},{"s":61945,"t":53,"tb":21,"h":0,"set":null},{"s":62000,"t":53,"tb":20,"h":0,"set":null},{"s":62130,"t":53,"tb":20,"h":0,"set":null},{"s":62231,"t":53,"tb":20,"h":0,"set":null},{"s":62303,"t":53,"tb":20,"h":0,"set":null},{"s":62345,"t":53,"tb":20,"h":0,"set":null},{"s":62407,"t":52,"tb":20,"h":0,"set":null},{"s":62447,"t":51,"tb":20,"h":0,"set":null},{"s":62527,"t":50,"tb":20,"h":0,"set":null},{"s":62600,"t":49,"tb":20,"h":0,"set":null},{"s":62648,"t":48,"tb":20,"h":0,"set":null},{"s":62717,"t":47,"tb":20,"h":0,"set":null},{"s":62768,"t":46,"tb":20,"h":0,"set":null},{"s":62818,"t":45,"tb":20,"h":0,"set":null},{"s":62870,"t":44,"tb":20,"h":0,"set":null},{"s":62920,"t":43,"tb":20,"h":0,"set":null},{"s":63011,"t":41,"tb":20,"h":0,"set":null},{"s":63053,"t":40,"tb":20,"h":0,"set":null},{"s":63145,"t":38,"tb":20,"h":0,"set":null},{"s":63186,"t":37,"tb":20,"h":0,"set":null},{"s":63265,"t":35,"tb":20,"h":0,"set":null},{"s":63309,"t":34,"tb":20,"h":0,"set":null},{"s":63353,"t":33,"tb":20,"h":0,"set":null},{"s":63394,"t":32,"tb":20,"h":0,"set":null},{"s":63495,"t":31,"tb":20,"h":0,"set":null},{"s":63592,"t":31,"tb":20,"h":0,"set":null},{"s":63673,"t":31,"tb":20,"h":0,"set":null},{"s":63727,"t":31,"tb":20,"h":0,"set":null},{"s":64309,"t":31,"tb":20,"h":0,"set":null},{"s":67575,"t":30,"tb":20,"h":0,"set":null},{"s":67610,"t":30,"tb":20,"h":0,"set":null},{"s":70213,"t":30,"tb":20,"h":1,"set":null},{"s":70599,"t":31,"tb":20,"h":1,"set":null},{"s":71063,"t":31,"tb":20,"h":1,"set":null},{"s":71112,"t":31,"tb":20,"h":1,"set":null},{"s":71178,"t":31,"tb":21,"h":1,"set":null},{"s":71224,"t":31,"tb":21,"h":1,"set":null},{"s":71480,"t":32,"tb":21,"h":1,"set":null},{"s":71508,"t":32,"tb":21,"h":1,"set":null},{"s":72018,"t":32,"tb":22,"h":1,"set":null},{"s":72042,"t":32,"tb":22,"h":1,"set":null},{"s":72230,"t":33,"tb":22,"h":1,"set":null},{"s":72540,"t":33,"tb":23,"h":1,"set":null},{"s":72679,"t":34,"tb":23,"h":1,"set":null},{"s":72800,"t":34,"tb":23,"h":1,"set":null},{"s":72822,"t":34,"tb":24,"h":1,"set":null},{"s":73104,"t":35,"tb":25,"h":1,"set":null},{"s":73455,"t":35,"tb":25,"h":1,"set":null},{"s":73510,"t":36,"tb":26,"h":1,"set":null},{"s":73704,"t":36,"tb":26,"h":1,"set":null},{"s":73733,"t":36,"tb":27,"h":1,"set":null},{"s":73874,"t":37,"tb":27,"h":1,"set":null},{"s":74108,"t":37,"tb":28,"h":1,"set":null},{"s":74287,"t":38,"tb":28,"h":1,"set":null},{"s":74348,"t":38,"tb":29,"h":1,"set":null},{"s":74655,"t":39,"tb":29,"h":1,"set":null},{"s":74738,"t":39,"tb":30,"h":1,"set":null},{"s":75046,"t":40,"tb":30,"h":1,"set":null},{"s":75133,"t":40,"tb":31,"h":1,"set":null},{"s":75448,"t":41,"tb":31,"h":1,"set":null},{"s":75537,"t":41,"tb":32,"h":1,"set":null},{"s":75833,"t":42,"tb":32,"h":1,"set":null},{"s":75938,"t":42,"tb":33,"h":1,"set":null},{"s":76254,"t":43,"tb":34,"h":1,"set":null},{"s":76526,"t":43,"tb":35,"h":1,"set":null},{"s":76653,"t":44,"tb":35,"h":1,"set":null},{"s":76836,"t":44,"tb":36,"h":1,"set":null},{"s":77084,"t":45,"tb":36,"h":1,"set":null},{"s":77168,"t":45,"tb":37,"h":1,"set":null},{"s":77400,"t":45,"tb":37,"h":1,"set":70},{"s":77526,"t":46,"tb":38,"h":1,"set":null},{"s":77847,"t":46,"tb":39,"h":1,"set":null},{"s":77990,"t":47,"tb":39,"h":1,"set":null},{"s":78197,"t":47,"tb":40,"h":1,"set":null},{"s":78426,"t":48,"tb":40,"h":1,"set":null},{"s":78560,"t":48,"tb":41,"h":1,"set":null},{"s":78642,"t":49,"tb":41,"h":1,"set":null},{"s":78717,"t":48,"tb":41,"h":1,"set":null},{"s":78925,"t":49,"tb":42,"h":1,"set":null},{"s":78940,"t":49,"tb":42,"h":1,"set":null},{"s":79306,"t":49,"tb":43,"h":1,"set":null},{"s":79409,"t":50,"tb":43,"h":1,"set":null},{"s":79750,"t":50,"tb":44,"h":1,"set":null},{"s":79900,"t":51,"tb":44,"h":1,"set":null},{"s":80201,"t":51,"tb":45,"h":1,"set":null},{"s":80464,"t":52,"tb":45,"h":1,"set":null},{"s":80657,"t":52,"tb":46,"h":1,"set":null},{"s":80705,"t":53,"tb":46,"h":1,"set":null},{"s":81155,"t":53,"tb":47,"h":1,"set":null},{"s":81251,"t":54,"tb":47,"h":1,"set":null},{"s":81572,"t":55,"tb":47,"h":1,"set":null},{"s":81742,"t":55,"tb":48,"h":1,"set":null},{"s":82095,"t":55,"tb":49,"h":1,"set":null},{"s":82176,"t":55,"tb":48,"h":1,"set":null},{"s":82240,"t":56,"tb":48,"h":1,"set":null},{"s":82429,"t":56,"tb":49,"h":1,"set":null},{"s":82568,"t":57,"tb":49,"h":1,"set":null},{"s":83040,"t":57,"tb":50,"h":1,"set":null},{"s":83326,"t":58,"tb":50,"h":1,"set":null},{"s":83710,"t":59,"tb":51,"h":1,"set":null},{"s":84379,"t":59,"tb":52,"h":1,"set":null},{"s":84527,"t":60,"tb":52,"h":1,"set":null},{"s":84886,"t":61,"tb":52,"h":1,"set":null},{"s":85313,"t":62,"tb":52,"h":1,"set":null},{"s":85356,"t":61,"tb":52,"h":1,"set":null},{"s":85440,"t":62,"tb":52,"h":1,"set":null},{"s":86400,"t":62,"tb":52,"h":1,"set":70}]},"recent":[{"date":"2026-07-23","min":56,"max":70,"avg":64.7,"avgBottom":43.5,"heatingMinutes":219,"cycles":1},{"date":"2026-07-22","min":21,"max":70,"avg":48.6,"avgBottom":34.4,"heatingMinutes":38,"cycles":3},{"date":"2026-07-21","min":51,"max":70,"avg":62.2,"avgBottom":36.5,"heatingMinutes":194,"cycles":3},{"date":"2026-07-20","min":29,"max":67,"avg":52.6,"avgBottom":31.8,"heatingMinutes":120,"cycles":3},{"date":"2026-07-19","min":41,"max":70,"avg":60.6,"avgBottom":29.5,"heatingMinutes":121,"cycles":3},{"date":"2026-07-18","min":48,"max":70,"avg":59.4,"avgBottom":28.9,"heatingMinutes":86,"cycles":3},{"date":"2026-07-17","min":30,"max":70,"avg":58.7,"avgBottom":33,"heatingMinutes":85,"cycles":3}]}